faizan/__init__.py
faizan/faizan.py
faizan-0.1.dist-info/METADATA
faizan-0.1.dist-info/WHEEL
faizan-0.1.dist-info/entry_points.txt
faizan-0.1.dist-info/top_level.txt
faizan-0.1.dist-info/RECORD
