Metadata-Version: 2.1
Name: faizan
Version: 0.1
Summary: An advanced tool for detecting and analyzing potential XSS payloads.
Home-page: https://github.com/faizan-khanx/XSS-DETECTOR
Author: Faizan Khan
Author-email: fk776794@gmail.com
Classifier: Programming Language :: Python :: 3
Classifier: License :: OSI Approved :: MIT License
Classifier: Operating System :: OS Independent
Classifier: Intended Audience :: Developers
Classifier: Intended Audience :: Information Technology
Classifier: Topic :: Security
Requires-Python: >=3.6
Requires-Dist: colorama
